pywalfox/__init__.py
pywalfox/__main__.py
pywalfox/config.py
pywalfox/custom_css.py
pywalfox/daemon.py
pywalfox/fetcher.py
pywalfox/install.py
pywalfox/messenger.py
pywalfox/response.py
pywalfox/assets/manifest.json
pywalfox/assets/css/userChrome.css
pywalfox/assets/css/userContent.css
pywalfox/bin/main.sh
pywalfox/bin/win.bat
pywalfox/channel/__init__.py
pywalfox/channel/connector.py
pywalfox/channel/unix/__init__.py
pywalfox/channel/unix/client.py
pywalfox/channel/unix/server.py
pywalfox/channel/win/__init__.py
pywalfox/channel/win/client.py
pywalfox/channel/win/server.py
pywalfox/utils/__init__.py
pywalfox/utils/logger.py
pywalfox-2.7.4.dist-info/LICENSE
pywalfox-2.7.4.dist-info/METADATA
pywalfox-2.7.4.dist-info/WHEEL
pywalfox-2.7.4.dist-info/entry_points.txt
pywalfox-2.7.4.dist-info/top_level.txt
pywalfox-2.7.4.dist-info/RECORD
