Metadata-Version: 2.1
Name: pywalfox
Version: 2.7.4
Summary: Native app used alongside the Pywalfox browser extension
Home-page: https://github.com/frewacom/pywalfox
Author: Fredrik Engstrand
Author-email: fredrik@engstrand.nu
License: MPL-2.0
Download-URL: https://github.com/Frewacom/pywalfox-native/archive/v2.7.4.tar.gz
Keywords: dynamic browser-theme firefox chrome duckduckgo unixporn native-messaging-host pywal colorscheme
Platform: UNKNOWN
Classifier: Topic :: Utilities
Classifier: Operating System :: POSIX :: Linux
Classifier: Operating System :: MacOS :: MacOS X
Classifier: Operating System :: Microsoft :: Windows
Classifier: Programming Language :: Python :: 2.7
Classifier: Programming Language :: Python :: 3
Classifier: License :: OSI Approved :: Mozilla Public License 2.0 (MPL 2.0)
Requires-Python: >=2.7
